asciigraf/VERSION
asciigraf/__init__.py
asciigraf/asciigraf.py
asciigraf/point.py
asciigraf/py.typed
asciigraf-1.1.1.dist-info/licenses/LICENSE.txt
asciigraf-1.1.1.dist-info/METADATA
asciigraf-1.1.1.dist-info/WHEEL
asciigraf-1.1.1.dist-info/top_level.txt
asciigraf-1.1.1.dist-info/RECORD
