Metadata-Version: 2.4
Name: asciigraf
Version: 1.1.1
Summary: A python library for making ascii-art into network graphs.
Author: Opus One Solutions
Author-email: rnd@opusonesolutions.com
License: copyright 2017 Anton Lodder
Project-URL: repository, https://github.com/opusonesolutions/asciigraf
Keywords: graph,network,parser,testing
Classifier: Development Status :: 3 - Alpha
Classifier: License :: OSI Approved :: MIT License
Classifier: Programming Language :: Python
Classifier: Programming Language :: Python :: 3 :: Only
Classifier: Programming Language :: Python :: 3.10
Classifier: Programming Language :: Python :: 3.11
Classifier: Programming Language :: Python :: 3.12
Classifier: Programming Language :: Python :: 3.13
Classifier: Topic :: Software Development :: Libraries :: Python Modules
Requires-Python: >=3.10
License-File: LICENSE.txt
Requires-Dist: colorama
Requires-Dist: networkx
Provides-Extra: test
Requires-Dist: liccheck; extra == "test"
Requires-Dist: pre-commit; extra == "test"
Requires-Dist: pytest; extra == "test"
Requires-Dist: pytest-cov; extra == "test"
Requires-Dist: setuptools; extra == "test"
Dynamic: license-file
